config/__init__.py
qmio/__init__.py
qmio/backends.py
qmio/circuits.py
qmio/clients.py
qmio/qmio.py
qmio/services.py
tests/__init__.py
tests/test_backends.py
tests/test_services.py
tests/test_zmq_client.py
qmio-0.1.3.dist-info/LICENSE
qmio-0.1.3.dist-info/METADATA
qmio-0.1.3.dist-info/WHEEL
qmio-0.1.3.dist-info/top_level.txt
qmio-0.1.3.dist-info/RECORD
