Metadata-Version: 2.1
Name: qmio
Version: 0.1.3
Summary: Helper python module to interact with the different backends available in Qmio.
Home-page: https://github.com/javicacheiro/qmio
Author: 'Javier Cacheiro, Alvaro Caride'
Author-email: 'javier.cacheiro@gmail.com, a.caride.sanchez@gmail.com'
License: Apache
Platform: UNKNOWN
License-File: LICENSE
Requires-Dist: pyzmq
Provides-Extra: test
Requires-Dist: pytest ; extra == 'test'
